setup.py
funcManager/funcManager.py
funcManager.egg-info/PKG-INFO
funcManager.egg-info/SOURCES.txt
funcManager.egg-info/dependency_links.txt
funcManager.egg-info/top_level.txt