Metadata-Version: 2.1
Name: funcManager
Version: 0.1.0
Summary: To allow classes to be dynamically added to a dictionary for more dynamic programming
Author: eejit
Author-email: help@eejitonline.uk
Classifier: Programming Language :: Python :: 3
Classifier: License :: OSI Approved :: MIT License
Classifier: Operating System :: OS Independent
Requires-Python: >=3.6
